flask_bulma_forms/__init__.py
flask_bulma_forms/static/css/bulma.css
flask_bulma_forms/static/css/bulma.css.map
flask_bulma_forms/static/css/bulma.min.css
flask_bulma_forms/static/js/jquery.js
flask_bulma_forms/static/js/jquery.min.js
flask_bulma_forms/static/js/jquery.min.map
flask_bulma_forms/static/js/jquery.slim.js
flask_bulma_forms/static/js/jquery.slim.min.js
flask_bulma_forms/static/js/jquery.slim.min.map
flask_bulma_forms/templates/bulma/base.html.j2
flask_bulma_forms/templates/bulma/utils.html.j2
flask_bulma_forms-0.8.3.dist-info/WHEEL
flask_bulma_forms-0.8.3.dist-info/METADATA
flask_bulma_forms-0.8.3.dist-info/RECORD
